{
  "id": "c7c49c51-2e50-4436-a055-c95efd44b9c5",
  "prevId": "00000000-0000-0000-0000-000000000000",
  "version": "7",
  "dialect": "postgresql",
  "tables": {
    "jungnang.apartments": {
      "name": "apartments",
      "schema": "jungnang",
      "columns": {
        "id": {
          "name": "id",
          "type": "bigserial",
          "primaryKey": true,
          "notNull": true
        },
        "sigungu_code": {
          "name": "sigungu_code",
          "type": "varchar(5)",
          "primaryKey": false,
          "notNull": true
        },
        "dong": {
          "name": "dong",
          "type": "varchar(50)",
          "primaryKey": false,
          "notNull": true
        },
        "jibun": {
          "name": "jibun",
          "type": "varchar(30)",
          "primaryKey": false,
          "notNull": false
        },
        "name": {
          "name": "name",
          "type": "varchar(200)",
          "primaryKey": false,
          "notNull": true
        },
        "building_year": {
          "name": "building_year",
          "type": "integer",
          "primaryKey": false,
          "notNull": false
        },
        "lat": {
          "name": "lat",
          "type": "numeric(10, 7)",
          "primaryKey": false,
          "notNull": false
        },
        "lon": {
          "name": "lon",
          "type": "numeric(10, 7)",
          "primaryKey": false,
          "notNull": false
        },
        "created_at": {
          "name": "created_at",
          "type": "timestamp with time zone",
          "primaryKey": false,
          "notNull": true,
          "default": "now()"
        },
        "updated_at": {
          "name": "updated_at",
          "type": "timestamp with time zone",
          "primaryKey": false,
          "notNull": true,
          "default": "now()"
        }
      },
      "indexes": {
        "apartments_dong_jibun_name_uniq": {
          "name": "apartments_dong_jibun_name_uniq",
          "columns": [
            {
              "expression": "dong",
              "isExpression": false,
              "asc": true,
              "nulls": "last"
            },
            {
              "expression": "jibun",
              "isExpression": false,
              "asc": true,
              "nulls": "last"
            },
            {
              "expression": "name",
              "isExpression": false,
              "asc": true,
              "nulls": "last"
            }
          ],
          "isUnique": true,
          "concurrently": false,
          "method": "btree",
          "with": {}
        },
        "apartments_sigungu_idx": {
          "name": "apartments_sigungu_idx",
          "columns": [
            {
              "expression": "sigungu_code",
              "isExpression": false,
              "asc": true,
              "nulls": "last"
            }
          ],
          "isUnique": false,
          "concurrently": false,
          "method": "btree",
          "with": {}
        }
      },
      "foreignKeys": {},
      "compositePrimaryKeys": {},
      "uniqueConstraints": {},
      "policies": {},
      "checkConstraints": {},
      "isRLSEnabled": false
    },
    "jungnang.realtors": {
      "name": "realtors",
      "schema": "jungnang",
      "columns": {
        "id": {
          "name": "id",
          "type": "bigserial",
          "primaryKey": true,
          "notNull": true
        },
        "registration_number": {
          "name": "registration_number",
          "type": "varchar(50)",
          "primaryKey": false,
          "notNull": false
        },
        "name": {
          "name": "name",
          "type": "varchar(200)",
          "primaryKey": false,
          "notNull": true
        },
        "representative": {
          "name": "representative",
          "type": "varchar(100)",
          "primaryKey": false,
          "notNull": false
        },
        "phone": {
          "name": "phone",
          "type": "varchar(30)",
          "primaryKey": false,
          "notNull": false
        },
        "address": {
          "name": "address",
          "type": "text",
          "primaryKey": false,
          "notNull": false
        },
        "dong": {
          "name": "dong",
          "type": "varchar(50)",
          "primaryKey": false,
          "notNull": false
        },
        "lat": {
          "name": "lat",
          "type": "numeric(10, 7)",
          "primaryKey": false,
          "notNull": false
        },
        "lon": {
          "name": "lon",
          "type": "numeric(10, 7)",
          "primaryKey": false,
          "notNull": false
        },
        "status": {
          "name": "status",
          "type": "varchar(20)",
          "primaryKey": false,
          "notNull": false
        },
        "source_key": {
          "name": "source_key",
          "type": "varchar(200)",
          "primaryKey": false,
          "notNull": true
        },
        "updated_at": {
          "name": "updated_at",
          "type": "timestamp with time zone",
          "primaryKey": false,
          "notNull": true,
          "default": "now()"
        }
      },
      "indexes": {
        "realtors_source_key_uniq": {
          "name": "realtors_source_key_uniq",
          "columns": [
            {
              "expression": "source_key",
              "isExpression": false,
              "asc": true,
              "nulls": "last"
            }
          ],
          "isUnique": true,
          "concurrently": false,
          "method": "btree",
          "with": {}
        },
        "realtors_dong_idx": {
          "name": "realtors_dong_idx",
          "columns": [
            {
              "expression": "dong",
              "isExpression": false,
              "asc": true,
              "nulls": "last"
            }
          ],
          "isUnique": false,
          "concurrently": false,
          "method": "btree",
          "with": {}
        },
        "realtors_geo_idx": {
          "name": "realtors_geo_idx",
          "columns": [
            {
              "expression": "lat",
              "isExpression": false,
              "asc": true,
              "nulls": "last"
            },
            {
              "expression": "lon",
              "isExpression": false,
              "asc": true,
              "nulls": "last"
            }
          ],
          "isUnique": false,
          "concurrently": false,
          "method": "btree",
          "with": {}
        }
      },
      "foreignKeys": {},
      "compositePrimaryKeys": {},
      "uniqueConstraints": {},
      "policies": {},
      "checkConstraints": {},
      "isRLSEnabled": false
    },
    "jungnang.transactions": {
      "name": "transactions",
      "schema": "jungnang",
      "columns": {
        "id": {
          "name": "id",
          "type": "bigserial",
          "primaryKey": true,
          "notNull": true
        },
        "apartment_id": {
          "name": "apartment_id",
          "type": "bigint",
          "primaryKey": false,
          "notNull": false
        },
        "sigungu_code": {
          "name": "sigungu_code",
          "type": "varchar(5)",
          "primaryKey": false,
          "notNull": true
        },
        "dong": {
          "name": "dong",
          "type": "varchar(50)",
          "primaryKey": false,
          "notNull": true
        },
        "jibun": {
          "name": "jibun",
          "type": "varchar(30)",
          "primaryKey": false,
          "notNull": false
        },
        "apartment_name": {
          "name": "apartment_name",
          "type": "varchar(200)",
          "primaryKey": false,
          "notNull": true
        },
        "lease_type": {
          "name": "lease_type",
          "type": "varchar(4)",
          "primaryKey": false,
          "notNull": true
        },
        "exclusive_area": {
          "name": "exclusive_area",
          "type": "numeric(10, 4)",
          "primaryKey": false,
          "notNull": true
        },
        "floor": {
          "name": "floor",
          "type": "integer",
          "primaryKey": false,
          "notNull": false
        },
        "contract_date": {
          "name": "contract_date",
          "type": "date",
          "primaryKey": false,
          "notNull": true
        },
        "deposit": {
          "name": "deposit",
          "type": "integer",
          "primaryKey": false,
          "notNull": true
        },
        "monthly_rent": {
          "name": "monthly_rent",
          "type": "integer",
          "primaryKey": false,
          "notNull": true,
          "default": 0
        },
        "contract_term_start": {
          "name": "contract_term_start",
          "type": "date",
          "primaryKey": false,
          "notNull": false
        },
        "contract_term_end": {
          "name": "contract_term_end",
          "type": "date",
          "primaryKey": false,
          "notNull": false
        },
        "contract_type": {
          "name": "contract_type",
          "type": "varchar(4)",
          "primaryKey": false,
          "notNull": false
        },
        "renewal_right_used": {
          "name": "renewal_right_used",
          "type": "boolean",
          "primaryKey": false,
          "notNull": false
        },
        "building_year": {
          "name": "building_year",
          "type": "integer",
          "primaryKey": false,
          "notNull": false
        },
        "source_key": {
          "name": "source_key",
          "type": "varchar(200)",
          "primaryKey": false,
          "notNull": true
        },
        "raw_payload": {
          "name": "raw_payload",
          "type": "jsonb",
          "primaryKey": false,
          "notNull": false
        },
        "ingested_at": {
          "name": "ingested_at",
          "type": "timestamp with time zone",
          "primaryKey": false,
          "notNull": true,
          "default": "now()"
        }
      },
      "indexes": {
        "transactions_source_key_uniq": {
          "name": "transactions_source_key_uniq",
          "columns": [
            {
              "expression": "source_key",
              "isExpression": false,
              "asc": true,
              "nulls": "last"
            }
          ],
          "isUnique": true,
          "concurrently": false,
          "method": "btree",
          "with": {}
        },
        "transactions_term_end_idx": {
          "name": "transactions_term_end_idx",
          "columns": [
            {
              "expression": "contract_term_end",
              "isExpression": false,
              "asc": true,
              "nulls": "last"
            }
          ],
          "isUnique": false,
          "concurrently": false,
          "method": "btree",
          "with": {}
        },
        "transactions_apartment_idx": {
          "name": "transactions_apartment_idx",
          "columns": [
            {
              "expression": "apartment_id",
              "isExpression": false,
              "asc": true,
              "nulls": "last"
            }
          ],
          "isUnique": false,
          "concurrently": false,
          "method": "btree",
          "with": {}
        },
        "transactions_dong_idx": {
          "name": "transactions_dong_idx",
          "columns": [
            {
              "expression": "dong",
              "isExpression": false,
              "asc": true,
              "nulls": "last"
            }
          ],
          "isUnique": false,
          "concurrently": false,
          "method": "btree",
          "with": {}
        }
      },
      "foreignKeys": {
        "transactions_apartment_id_apartments_id_fk": {
          "name": "transactions_apartment_id_apartments_id_fk",
          "tableFrom": "transactions",
          "tableTo": "apartments",
          "schemaTo": "jungnang",
          "columnsFrom": [
            "apartment_id"
          ],
          "columnsTo": [
            "id"
          ],
          "onDelete": "no action",
          "onUpdate": "no action"
        }
      },
      "compositePrimaryKeys": {},
      "uniqueConstraints": {},
      "policies": {},
      "checkConstraints": {},
      "isRLSEnabled": false
    }
  },
  "enums": {},
  "schemas": {
    "jungnang": "jungnang"
  },
  "sequences": {},
  "roles": {},
  "policies": {},
  "views": {},
  "_meta": {
    "columns": {},
    "schemas": {},
    "tables": {}
  }
}